spark_mock/__init__.py
spark_mock/core/__init__.py
spark_mock/core/execution.py
spark_mock/core/lazy.py
spark_mock/core/partition.py
spark_mock/io/__init__.py
spark_mock/io/reader.py
spark_mock/io/writer.py
spark_mock/sql/__init__.py
spark_mock/sql/catalog.py
spark_mock/sql/column.py
spark_mock/sql/dataframe.py
spark_mock/sql/functions.py
spark_mock/sql/row.py
spark_mock/sql/session.py
spark_mock/sql/sql_parser.py
spark_mock/sql/types.py
spark_mock/sql/window.py
spark_mock/ui/__init__.py
spark_mock/ui/console.py
spark_mock/ui/html_ui.py
spark_mock/ui/metrics.py
spark_mock/utils/__init__.py
spark_mock-0.1.0.dist-info/licenses/LICENSE
spark_mock-0.1.0.dist-info/METADATA
spark_mock-0.1.0.dist-info/WHEEL
spark_mock-0.1.0.dist-info/top_level.txt
spark_mock-0.1.0.dist-info/RECORD
