Metadata-Version: 2.4
Name: spark-mock
Version: 0.1.0
Summary: A mock Apache Spark implementation using Polars backend for learning and testing
Author-email: "DataLearn.dev" <contact@datalearn.dev>
Maintainer-email: "DataLearn.dev" <contact@datalearn.dev>
License: MIT
Project-URL: Homepage, https://datalearn.dev
Project-URL: Documentation, https://github.com/datalearn-dev/spark-mock#readme
Project-URL: Repository, https://github.com/datalearn-dev/spark-mock.git
Project-URL: Issues, https://github.com/datalearn-dev/spark-mock/issues
Keywords: spark,pyspark,mock,polars,dataframe,big-data,data-engineering,learning
Classifier: Development Status :: 3 - Alpha
Classifier: Intended Audience :: Developers
Classifier: Intended Audience :: Education
Classifier: License :: OSI Approved :: MIT License
Classifier: Operating System :: OS Independent
Classifier: Programming Language :: Python :: 3
Classifier: Programming Language :: Python :: 3.9
Classifier: Programming Language :: Python :: 3.10
Classifier: Programming Language :: Python :: 3.11
Classifier: Programming Language :: Python :: 3.12
Classifier: Programming Language :: Python :: 3.13
Classifier: Topic :: Software Development :: Libraries :: Python Modules
Classifier: Topic :: Education
Requires-Python: >=3.9
License-File: LICENSE
Requires-Dist: polars>=0.20.0
Requires-Dist: rich>=13.0.0
Requires-Dist: sqlglot>=20.0.0
Provides-Extra: dev
Requires-Dist: pytest>=7.0.0; extra == "dev"
Requires-Dist: pytest-cov>=4.0.0; extra == "dev"
Dynamic: license-file
